torchgist/__init__.py
torchgist/models/__init__.py
torchgist/models/models.py
torchgist-1.0.0.dist-info/LICENSE
torchgist-1.0.0.dist-info/METADATA
torchgist-1.0.0.dist-info/WHEEL
torchgist-1.0.0.dist-info/top_level.txt
torchgist-1.0.0.dist-info/RECORD
